{
  "schema": "astra-home-status-v0.1",
  "generatedAt": "2026-05-12T18:22:23.347Z",
  "project": "AstraTreasury Protocol",
  "version": "0.1.1",
  "branch": "main",
  "shortCommit": "524aa01",
  "publicStatement": "AstraTreasury is deployed on Base Mainnet in restricted operational mode. Public token sale, real treasury funding, staking/rewards, buybacks, autonomous execution, and mainnet execution queue activation remain disabled.",
  "network": {
    "name": "Base Mainnet",
    "chainId": 8453
  },
  "summary": {
    "contractCount": 5,
    "liveStatus": "MAINNET_CONTRACTS_DEPLOYED_RESTRICTED_OPERATION",
    "launchStatus": "RESTRICTED_LAUNCH_READY",
    "monitorStatus": "PASS",
    "alertsResponseRequired": false,
    "activeIncidents": 0,
    "roadmapStatus": "CAPABILITY_ROADMAP_READY",
    "stabilizationStatus": "RESTRICTED_LAUNCH_STABILIZED",
    "packageCount": 22
  },
  "restrictions": {
    "publicTokenSale": false,
    "realTreasuryFunding": false,
    "stakingOrRewards": false,
    "buybackProgram": false,
    "autonomousExecution": false,
    "mainnetExecutionQueue": false
  },
  "primaryLinks": {
    "mainnet": "/mainnet",
    "live": "/live",
    "monitor": "/monitor",
    "launch": "/launch",
    "announcement": "/announcement",
    "transparency": "/transparency",
    "roadmap": "/roadmap"
  }
}
